AddBox.sv
// Generator : SpinalHDL v1.3.8    git head : 57d97088b91271a094cebad32ed86479199955df
// Date      : 10/03/2020, 11:27:58
// Component : Add


module AddBox (
      input   a,
      output reg  c,
      input   clk,
      input   reset);
  always @ (posedge clk) begin
    c <= a;
  end

endmodule

Verilog/TopLevel.v
// Generator : SpinalHDL v1.3.8    git head : 57d97088b91271a094cebad32ed86479199955df
// Date      : 10/03/2020, 11:27:35
// Component : TopLevel


module TopLevel (
      input   io_a,
      output  io_c,
      input   reset,
      input   clk);
  wire  add_c;
  AddBox add ( 
    .clk(clk),
    .reset(reset),
    .a(io_a),
    .c(add_c) 
  );
  assign io_c = add_c;
endmodule

simWorkspace/TopLevel/test.vcd
$version Generated by VerilatedVcd $end
$date Tue Mar 10 11:42:16 2020
 $end
$timescale   1ns $end

 $scope module TOP $end
  $var wire  1 ' clk $end
  $var wire  1 $ io_a $end
  $var wire  1 % io_c $end
  $var wire  1 & reset $end
  $scope module TopLevel $end
   $var wire  1 # add_c $end
   $var wire  1 ' clk $end
   $var wire  1 $ io_a $end
   $var wire  1 % io_c $end
   $var wire  1 & reset $end
   $scope module add $end
    $var wire  1 $ a $end
    $var wire  1 # c $end
    $var wire  1 ' clk $end
    $var wire  1 & reset $end
   $upscope $end
  $upscope $end
 $upscope $end
$enddefinitions $end


#0
0#
0$
0%
1&
0'
#160
0&
#170
1$
1'
#175
0'
#180
1#
1%
1'
#185
0'
#190
1'
#195
0'
#200
1'
#205
0'
#210
1'
#215
0'
#220
0$
1'
#225
0'
#230
0#
1$
0%
1'
#235
0'
#240
1#
1%
1'
#245
0'
#250
0$
1'
#255
0'
#260
0#
1$
0%
1'
#265
0'
#270
1#
0$
1%
1'
#275
0'
#280
0#
0%
1'
#285
0'
#290
1'
#295
0'
#300
1$
1'
#305
0'
#310
1#
1%
1'
#315
0'
#320
1'
#325
0'
#330
0$
1'
#335
0'
#340
0#
1$
0%
1'
#345
0'
#350
1#
0$
1%
1'
#355
0'
#360
0#
0%
1'
#365
0'
#370
1'
#375
0'
#380
1$
1'
#385
0'
#390
1#
1%
1'
#395
0'
#400
0$
1'
#405
0'
#410
0#
1$
0%
1'
#415
0'
#420
1#
1%
1'
#425
0'
#430
1'
#435
0'
#440
0$
1'
#445
0'
#450
0#
1$
0%
1'
#455
0'
#460
1#
1%
1'
#465
0'
#470
0$
1'
#475
0'
#480
0#
0%
1'
#485
0'
#490
1'
#495
0'
#500
1'
#505
0'
#510
1'
#515
0'
#520
1'
#525
0'
#530
1$
1'
#535
0'
#540
1#
0$
1%
1'
#545
0'
#550
0#
1$
0%
1'
#555
0'
#560
1#
0$
1%
1'
#565
0'
#570
0#
1$
0%
1'
#575
0'
#580
1#
1%
1'
#585
0'
#590
0$
1'
#595
0'
#600
0#
1$
0%
1'
#605
0'
#610
1#
1%
1'
#615
0'
#620
1'
#625
0'
#630
0$
1'
#635
0'
#640
0#
1$
0%
1'
#645
0'
#650
1#
1%
1'
#655
0'
#660
0$
1'
#665
0'
#670
0#
0%
1'
#675
0'
#680
1$
1'
#685
0'
#690
1#
0$
1%
1'
#695
0'
#700
0#
0%
1'
#705
0'
#710
1$
1'
#715
0'
#720
1#
1%
1'
#725
0'
#730
1'
#735
0'
#740
1'
#745
0'
#750
0$
1'
#755
0'
#760
0#
1$
0%
1'
#765
0'
#770
1#
0$
1%
1'
#775
0'
#780
0#
1$
0%
1'
#785
0'
#790
1#
0$
1%
1'
#795
0'
#800
0#
0%
1'
#805
0'
#810
1$
1'
#815
0'
#820
1#
1%
1'
#825
0'
#830
0$
1'
#835
0'
#840
0#
0%
1'
#845
0'
#850
1$
1'
#855
0'
#860
1#
0$
1%
1'
#865
0'
#870
0#
0%
1'
#875
0'
#880
1$
1'
#885
0'
#890
1#
1%
1'
#895
0'
#900
0$
1'
#905
0'
#910
0#
1$
0%
1'
#915
0'
#920
1#
0$
1%
1'
#925
0'
#930
0#
1$
0%
1'
#935
0'
#940
1#
0$
1%
1'
#945
0'
#950
0#
0%
1'
#955
0'
#960
1$
1'
#965
0'
#970
1#
1%
1'
#975
0'
#980
1'
#985
0'
#990
0$
1'
#995
0'
#1000
0#
0%
1'
#1005
0'
#1010
1$
1'
#1015
0'
#1020
1#
1%
1'
#1025
0'
#1030
0$
1'
#1035
0'
#1040
0#
0%
1'
#1045
0'
#1050
1$
1'
#1055
0'
#1060
1#
1%
1'
#1065
0'
#1070
1'
#1075
0'
#1080
1'
#1085
0'
#1090
1'
#1095
0'
#1100
0$
1'
#1105
0'
#1110
0#
1$
0%
1'
#1115
0'
#1120
1#
1%
1'
#1125
0'
#1130
0$
1'
#1135
0'
#1140
0#
0%
1'
