tmp/job_1/MyTopLevel.v
// Generator : SpinalHDL v1.3.8    git head : 57d97088b91271a094cebad32ed86479199955df
// Date      : 10/03/2020, 11:23:25
// Component : MyTopLevel


module MyTopLevel (
      input   io_cond0,
      input   io_cond1,
      output  io_flag,
      output [7:0] io_state,
      input   clk,
      input   reset);
  reg [7:0] counter;
  assign io_state = counter;
  assign io_flag = ((counter == (8'b00000000)) || io_cond1);
  always @ (posedge clk or posedge reset) begin
    if (reset) begin
      counter <= (8'b00000000);
    end else begin
      if(io_cond0)begin
        counter <= (counter + (8'b00000001));
      end
    end
  end

endmodule

simWorkspace/MyTopLevel/test.vcd
$version Generated by VerilatedVcd $end
$date Tue Mar 10 11:23:29 2020
 $end
$timescale   1ns $end

 $scope module TOP $end
  $var wire  1 ( clk $end
  $var wire  1 $ io_cond0 $end
  $var wire  1 % io_cond1 $end
  $var wire  1 & io_flag $end
  $var wire  8 ' io_state [7:0] $end
  $var wire  1 ) reset $end
  $scope module MyTopLevel $end
   $var wire  1 ( clk $end
   $var wire  8 # counter [7:0] $end
   $var wire  1 $ io_cond0 $end
   $var wire  1 % io_cond1 $end
   $var wire  1 & io_flag $end
   $var wire  8 ' io_state [7:0] $end
   $var wire  1 ) reset $end
  $upscope $end
 $upscope $end
$enddefinitions $end


#0
b00000000 #
1$
1%
1&
b00000000 '
0(
1)
#160
0)
#170
b00000001 #
0%
0&
b00000001 '
1(
#175
0(
#180
b00000010 #
0$
1%
1&
b00000010 '
1(
#185
0(
#190
1$
1(
#195
0(
#200
b00000011 #
0%
0&
b00000011 '
1(
#205
0(
#210
b00000100 #
0$
b00000100 '
1(
#215
0(
#220
1$
1(
#225
0(
#230
b00000101 #
0$
1%
1&
b00000101 '
1(
#235
0(
#240
1(
#245
0(
#250
1$
1(
#255
0(
#260
b00000110 #
0$
b00000110 '
1(
#265
0(
#270
1$
1(
#275
0(
#280
b00000111 #
0%
0&
b00000111 '
1(
#285
0(
#290
b00001000 #
0$
1%
1&
b00001000 '
1(
#295
0(
#300
1(
#305
0(
#310
1(
#315
0(
#320
1(
#325
0(
#330
1$
1(
#335
0(
#340
b00001001 #
b00001001 '
1(
#345
0(
#350
b00001010 #
0$
0%
0&
b00001010 '
1(
#355
0(
#360
1(
#365
0(
#370
1$
1%
1&
1(
#375
0(
#380
b00001011 #
0%
0&
b00001011 '
1(
#385
0(
#390
b00001100 #
1%
1&
b00001100 '
1(
#395
0(
#400
b00001101 #
0%
0&
b00001101 '
1(
#405
0(
#410
b00001110 #
b00001110 '
1(
#415
0(
#420
b00001111 #
b00001111 '
1(
#425
0(
#430
b00010000 #
b00010000 '
1(
#435
0(
#440
b00010001 #
1%
1&
b00010001 '
1(
#445
0(
#450
b00010010 #
b00010010 '
1(
#455
0(
#460
b00010011 #
b00010011 '
1(
#465
0(
#470
b00010100 #
0$
0%
0&
b00010100 '
1(
#475
0(
#480
1(
#485
0(
#490
1$
1%
1&
1(
#495
0(
#500
b00010101 #
0$
b00010101 '
1(
#505
0(
#510
0%
0&
1(
#515
0(
#520
1(
#525
0(
#530
1$
1(
#535
0(
#540
b00010110 #
b00010110 '
1(
#545
0(
#550
b00010111 #
0$
b00010111 '
1(
#555
0(
#560
1(
#565
0(
#570
1(
#575
0(
#580
1$
1%
1&
1(
#585
0(
#590
b00011000 #
0%
0&
b00011000 '
1(
#595
0(
#600
b00011001 #
0$
b00011001 '
1(
#605
0(
#610
1(
#615
0(
#620
1%
1&
1(
#625
0(
#630
1(
#635
0(
#640
1$
0%
0&
1(
#645
0(
#650
b00011010 #
0$
1%
1&
b00011010 '
1(
#655
0(
#660
1$
1(
#665
0(
#670
b00011011 #
0$
0%
0&
b00011011 '
1(
#675
0(
#680
1%
1&
1(
#685
0(
#690
1(
#695
0(
#700
1(
#705
0(
#710
1$
1(
#715
0(
#720
b00011100 #
0$
0%
0&
b00011100 '
1(
#725
0(
#730
1%
1&
1(
#735
0(
#740
1$
0%
0&
1(
#745
0(
#750
b00011101 #
1%
1&
b00011101 '
1(
#755
0(
#760
b00011110 #
0%
0&
b00011110 '
1(
#765
0(
#770
b00011111 #
0$
b00011111 '
1(
#775
0(
#780
1$
1(
#785
0(
#790
b00100000 #
b00100000 '
1(
#795
0(
#800
b00100001 #
b00100001 '
1(
#805
0(
#810
b00100010 #
b00100010 '
1(
#815
0(
#820
b00100011 #
0$
b00100011 '
1(
#825
0(
#830
1(
#835
0(
#840
1(
#845
0(
#850
1$
1%
1&
1(
#855
0(
#860
b00100100 #
0$
0%
0&
b00100100 '
1(
#865
0(
#870
1(
#875
0(
#880
1$
1(
#885
0(
#890
b00100101 #
1%
1&
b00100101 '
1(
#895
0(
#900
b00100110 #
0%
0&
b00100110 '
1(
#905
0(
#910
b00100111 #
0$
1%
1&
b00100111 '
1(
#915
0(
#920
1(
#925
0(
#930
0%
0&
1(
#935
0(
#940
1$
1%
1&
1(
#945
0(
#950
b00101000 #
0%
0&
b00101000 '
1(
#955
0(
#960
b00101001 #
0$
b00101001 '
1(
#965
0(
#970
1%
1&
1(
#975
0(
#980
1$
0%
0&
1(
#985
0(
#990
b00101010 #
0$
1%
1&
b00101010 '
1(
#995
0(
#1000
1$
1(
#1005
0(
#1010
b00101011 #
b00101011 '
1(
#1015
0(
#1020
b00101100 #
b00101100 '
1(
#1025
0(
#1030
b00101101 #
0$
0%
0&
b00101101 '
1(
#1035
0(
#1040
1$
1%
1&
1(
#1045
0(
#1050
b00101110 #
0$
b00101110 '
1(
#1055
0(
#1060
1$
0%
0&
1(
#1065
0(
#1070
b00101111 #
0$
b00101111 '
1(
#1075
0(
#1080
1%
1&
1(
#1085
0(
#1090
1$
1(
#1095
0(
#1100
b00110000 #
b00110000 '
1(
#1105
0(
#1110
b00110001 #
0$
b00110001 '
1(
#1115
0(
#1120
1$
0%
0&
1(
#1125
0(
#1130
b00110010 #
0$
1%
1&
b00110010 '
1(
#1135
0(
#1140
0%
0&
1(
#1145
0(
#1150
1%
1&
1(
